MANIFEST.in
README.rst
setup.py
doc/Makefile
doc/__init__.py
doc/choices.rst
doc/conf.py
doc/filters.rst
doc/index.rst
doc/lck.django.activitylog.middleware.rst
doc/lck.django.activitylog.models.rst
doc/lck.django.badges.models.rst
doc/lck.django.cache.rst
doc/lck.django.choices.rst
doc/lck.django.common.forms.rst
doc/lck.django.common.middleware.rst
doc/lck.django.common.models.rst
doc/lck.django.common.rst
doc/lck.django.common.templatetags.bbcode.rst
doc/lck.django.common.templatetags.converters.rst
doc/lck.django.common.templatetags.cycle_filter.rst
doc/lck.django.common.templatetags.strings.rst
doc/lck.django.common.templatetags.thumbnail.rst
doc/lck.django.filters.rst
doc/lck.django.profile.models.rst
doc/lck.django.score.models.rst
doc/lck.django.score.templatetags.lckd_score.rst
doc/lck.django.tags.helpers.rst
doc/lck.django.tags.models.rst
doc/license.rst
doc/make.bat
doc/manage.rst
doc/overview.rst
doc/settings.rst
doc/todo.rst
doc/theme/ADCtheme/LICENSE
doc/theme/ADCtheme/README.rst
doc/theme/ADCtheme/layout.html
doc/theme/ADCtheme/theme.conf
doc/theme/ADCtheme/static/adctheme.css
doc/theme/ADCtheme/static/breadcrumb_background.png
doc/theme/ADCtheme/static/documentation.png
doc/theme/ADCtheme/static/header_sm_mid.png
doc/theme/ADCtheme/static/scrn1.png
doc/theme/ADCtheme/static/scrn2.png
doc/theme/ADCtheme/static/searchfield_leftcap.png
doc/theme/ADCtheme/static/searchfield_repeat.png
doc/theme/ADCtheme/static/searchfield_rightcap.png
doc/theme/ADCtheme/static/title_background.png
doc/theme/ADCtheme/static/toc.js
doc/theme/ADCtheme/static/triangle_closed.png
doc/theme/ADCtheme/static/triangle_left.png
doc/theme/ADCtheme/static/triangle_open.png
src/lck/__init__.py
src/lck.django.egg-info/PKG-INFO
src/lck.django.egg-info/SOURCES.txt
src/lck.django.egg-info/dependency_links.txt
src/lck.django.egg-info/namespace_packages.txt
src/lck.django.egg-info/not-zip-safe
src/lck.django.egg-info/requires.txt
src/lck.django.egg-info/top_level.txt
src/lck/django/__init__.py
src/lck/django/cache.py
src/lck/django/cache_backends.py
src/lck/django/choices.py
src/lck/django/current_dir_support.py
src/lck/django/filters.py
src/lck/django/manage.py
src/lck/django/metaclasses.py
src/lck/django/namespace_package_support.py
